CHANGES.rst
MANIFEST.in
README.rst
setup.cfg
setup.py
xibless/__init__.py
xibless/base.py
xibless/button.py
xibless/color.py
xibless/combo.py
xibless/control.py
xibless/font.py
xibless/formatter.py
xibless/gen.py
xibless/globalvars.py
xibless/image.py
xibless/layout.py
xibless/menu.py
xibless/popup.py
xibless/progress.py
xibless/property.py
xibless/radio.py
xibless/segment.py
xibless/slider.py
xibless/splitview.py
xibless/table.py
xibless/tabview.py
xibless/textfield.py
xibless/textview.py
xibless/toolbar.py
xibless/types.py
xibless/util.py
xibless/view.py
xibless/window.py
xibless.egg-info/PKG-INFO
xibless.egg-info/SOURCES.txt
xibless.egg-info/dependency_links.txt
xibless.egg-info/entry_points.txt
xibless.egg-info/top_level.txt
xibless/data/XiblessSupport.h
xibless/data/XiblessSupport.m
xibless/runtemplate/Info.plist
xibless/runtemplate/MainMenu.py
xibless/runtemplate/main.m
xibless/runtemplate/waf
xibless/runtemplate/wscript