Metadata-Version: 1.1
Name: xibless
Version: 0.5.1
Summary: Generate Objective-C code that builds Cocoa UIs. Replaces XCode's XIBs
Home-page: https://github.com/hsoft/xibless/
Author: Virgil Dupras
Author-email: hsoft@hardcoded.net
License: BSD
Platform: UNKNOWN
Classifier: Development Status :: 3 - Alpha
Classifier: Intended Audience :: Developers
Classifier: Environment :: Console
Classifier: License :: OSI Approved :: BSD License
Classifier: Operating System :: MacOS :: MacOS X
Classifier: Programming Language :: Python :: 2.7
Classifier: Programming Language :: Python :: 3
Classifier: Programming Language :: Objective C
Classifier: Topic :: Software Development :: Code Generators
